deepprotein/__init__.py
deepprotein/_version.py
deepprotein-0.0.0.dist-info/METADATA
deepprotein-0.0.0.dist-info/WHEEL
deepprotein-0.0.0.dist-info/top_level.txt
deepprotein-0.0.0.dist-info/RECORD
